electronex/__init__.py
electronex/algorithms.py
electronex/circuits.py
electronex/comms.py
electronex/dsp.py
electronex/logic.py
electronex/mltools.py
electronex/signals.py
electronex/utils.py
electronex/visualization.py
electronex-1.4.0.dist-info/licenses/LICENSE
electronex-1.4.0.dist-info/METADATA
electronex-1.4.0.dist-info/WHEEL
electronex-1.4.0.dist-info/top_level.txt
electronex-1.4.0.dist-info/RECORD
