Metadata-Version: 2.4
Name: electronex
Version: 1.4.0
Summary: Python package for ECE & CSE engineering utilities
Home-page: https://github.com/hrishabhxcode/enginex
Author: Hrishabh
Author-email: hrishabhtest@gmail.com
Classifier: Programming Language :: Python :: 3
Classifier: License :: OSI Approved :: MIT License
Classifier: Operating System :: OS Independent
Requires-Python: >=3.7, <4
License-File: LICENSE
Requires-Dist: numpy
Requires-Dist: matplotlib
Dynamic: author
Dynamic: author-email
Dynamic: classifier
Dynamic: description
Dynamic: description-content-type
Dynamic: home-page
Dynamic: license-file
Dynamic: requires-dist
Dynamic: requires-python
Dynamic: summary
